CHANGES.txt
DEPENDENCIES.txt
README.txt
bootstrap.py
buildout.cfg
setup.py
src/ks/__init__.py
src/ks.channel.egg-info/PKG-INFO
src/ks.channel.egg-info/SOURCES.txt
src/ks.channel.egg-info/dependency_links.txt
src/ks.channel.egg-info/namespace_packages.txt
src/ks.channel.egg-info/not-zip-safe
src/ks.channel.egg-info/requires.txt
src/ks.channel.egg-info/top_level.txt
src/ks/channel/__init__.py
src/ks/channel/channel.txt
src/ks/channel/configure.zcml
src/ks/channel/interfaces.py
src/ks/channel/vocabulary.py
src/ks/channel/etc/ks.channel-configure.zcml